sterra/SterraException.py
sterra/__init__.py
sterra/__main__.py
sterra/_logo_.py
sterra/_outputs_.py
sterra/_sterrage_.py
sterra/_userAgents_.py
sterra/comparerra.py
sterra/core.py
sterra/exterra.py
sterra/filerra.py
sterra/histerra.py
sterra/stanalysis.py
sterra/stegram.py
sterra/sterools.py
sterra-2.2.5.dist-info/LICENCE
sterra-2.2.5.dist-info/METADATA
sterra-2.2.5.dist-info/WHEEL
sterra-2.2.5.dist-info/entry_points.txt
sterra-2.2.5.dist-info/top_level.txt
sterra-2.2.5.dist-info/RECORD
