Metadata-Version: 2.1
Name: sterra
Version: 2.2.5
Home-page: https://github.com/novitae/sterraxcyl
Author: novitae
License: GNU General Public License v3 (GPLv3)
Classifier: Programming Language :: Python :: 3.9
License-File: LICENCE
Requires-Dist: aiohttp
Requires-Dist: argparse
Requires-Dist: datetime
Requires-Dist: openpyxl
Requires-Dist: requests
Requires-Dist: string-color
Requires-Dist: tqdm
